locus/__init__.py
locus/kd.py
locus/py.typed
locus/r.py
locus/segmental.py
locus/_core/__init__.py
locus/_core/box.py
locus/_core/hilbert.py
locus/_core/hints.py
locus/_core/kd.py
locus/_core/r.py
locus/_core/segmental.py
locus/_core/utils.py
locus-11.0.0.dist-info/licenses/LICENSE
locus-11.0.0.dist-info/METADATA
locus-11.0.0.dist-info/WHEEL
locus-11.0.0.dist-info/top_level.txt
locus-11.0.0.dist-info/RECORD
